pydlltoolkit/__init__.py
pydlltoolkit/script.py
pydlltoolkit-0.1.1.dist-info/METADATA
pydlltoolkit-0.1.1.dist-info/WHEEL
pydlltoolkit-0.1.1.dist-info/top_level.txt
pydlltoolkit-0.1.1.dist-info/RECORD
