Metadata-Version: 2.4
Name: pydlltoolkit
Version: 0.1.1
Summary: Python DLL Injection Toolkit
Home-page: https://github.com/CodeChakkra/pydlltoolkit
Author: CodeChakkra
Author-email: ttenwi888@gmail.com
Requires-Python: >=3.13
Requires-Dist: pywin32>=300
Dynamic: author
Dynamic: author-email
Dynamic: description
Dynamic: description-content-type
Dynamic: home-page
Dynamic: requires-dist
Dynamic: requires-python
Dynamic: summary
